CHANGELOG.md
LICENSE
MANIFEST.in
Makefile
README.md
setup.cfg
setup.py
tox.ini
wc_html2pdf/__init__.py
wc_html2pdf.egg-info/PKG-INFO
wc_html2pdf.egg-info/SOURCES.txt
wc_html2pdf.egg-info/dependency_links.txt
wc_html2pdf.egg-info/requires.txt
wc_html2pdf.egg-info/top_level.txt
wc_html2pdf/contrib/__init__.py
wc_html2pdf/contrib/django/__init__.py
wc_html2pdf/contrib/django/apps.py
wc_html2pdf/contrib/django/shortcuts.py
wc_html2pdf/contrib/django/url_getters.py
wc_html2pdf/contrib/django/views.py
wc_html2pdf/contrib/django/jinja/__init__.py
wc_html2pdf/contrib/django/jinja/extensions.py
wc_html2pdf/contrib/django/templatetags/__init__.py
wc_html2pdf/contrib/django/templatetags/html2pdf.py
wc_html2pdf/converters/__init__.py
wc_html2pdf/converters/base.py
wc_html2pdf/converters/chromium.py
wc_html2pdf/converters/weasyprint.py