Metadata-Version: 2.1
Name: wc-html2pdf
Version: 0.1.0
Summary: HTML to PDF conversion utilities.
Author: WebCase
Author-email: info@webcase.studio
License: MIT License
Classifier: Development Status :: 2 - Pre-Alpha
Classifier: Programming Language :: Python :: 3
Classifier: Intended Audience :: Developers
Classifier: Topic :: Utilities
Classifier: License :: OSI Approved :: MIT License
Classifier: Operating System :: OS Independent
Requires-Python: >=3.6
Provides-Extra: dev
License-File: LICENSE
